cormen_lib/__init__.py
cormen_lib/arrays.py
cormen_lib/factory_utils.py
cormen_lib/graphs.py
cormen_lib/hashing.py
cormen_lib/heaps.py
cormen_lib/linked_lists.py
cormen_lib/misc_utils.py
cormen_lib/queues.py
cormen_lib/sets.py
cormen_lib/stacks.py
cormen_lib/test_utils.py
cormen_lib/trees.py
cormen_lib-1.1.3.dist-info/LICENSE
cormen_lib-1.1.3.dist-info/METADATA
cormen_lib-1.1.3.dist-info/WHEEL
cormen_lib-1.1.3.dist-info/top_level.txt
cormen_lib-1.1.3.dist-info/RECORD
