Metadata-Version: 2.1
Name: cormen-lib
Version: 1.1.3
Summary: A data structures and algorithms library based on Introduction to Algorithms Third Edition by Thomas H. Cormen.
Home-page: https://pypi.org/project/dalpy/
Author: Eitan Joseph, Chami Lamelas
Author-email: eitanjoseph@brandeis.edu
License: UNKNOWN
Platform: all
License-File: LICENSE
Requires-Dist: dalpy
